anthropic_mock_wrapper/__init__.py
anthropic_mock_wrapper/wrapper.py
anthropic_mock_wrapper-0.2.10.dist-info/LICENSE
anthropic_mock_wrapper-0.2.10.dist-info/METADATA
anthropic_mock_wrapper-0.2.10.dist-info/WHEEL
anthropic_mock_wrapper-0.2.10.dist-info/top_level.txt
anthropic_mock_wrapper-0.2.10.dist-info/RECORD
