Metadata-Version: 2.1
Name: anthropic_mock_wrapper
Version: 0.2.10
Summary: A lightweight wrapper around the Anthropic Python client for testing purposes
Home-page: https://github.com/ps2-controller/anthropic_mock_wrapper
Author: Anurag Angara
Author-email: anurag.angara@gmail.com
Classifier: Programming Language :: Python :: 3
Classifier: License :: OSI Approved :: MIT License
Classifier: Operating System :: OS Independent
Requires-Python: >=3.7
License-File: LICENSE
Requires-Dist: anthropic
Requires-Dist: lorem
Provides-Extra: dev
Requires-Dist: mypy; extra == "dev"
Requires-Dist: pytest; extra == "dev"
Requires-Dist: pytest-asyncio; extra == "dev"
